fsm.v
//For starting from a particular state(s0), reset input has also been used which was not present in the state machine diagram. 
`timescale 1ns/1ns
module fsm(
  input A,
  input clock,
  input reset,
  output [1:0]Z
	);
  
  reg [1:0] present_state,next_state;
  parameter s0 = 0, s1 = 1, s2 = 2, s3 = 3;
  
// Block for defining what happens when reset is asserted and if not
  always @(posedge clock)  
	begin 
 		if (reset) 
 			present_state <= s0; 
 		else 
 			present_state <= next_state; 
    end 
  
//State Transition block
  always @(*)
    case(present_state)
      s0:begin
        case(A)
           1'b0:next_state=s3; 
           1'b1:next_state=s1; 
        endcase
      end
      s1:begin
        case(A)
           1'b0:next_state=s0; 
           1'b1:next_state=s2; 
        endcase
      end
      s2:begin
        case(A)
           1'b0:next_state=s1; 
           1'b1:next_state=s3; 
        endcase
      end
      s3:begin
        case(A)
           1'b0:next_state=s2; 
           1'b1:next_state=s0; 
        endcase
      end
    endcase
  
  	assign Z = present_state; 
endmodule

fsm_tb.v
`timescale 1ns/1ns

module fsm_tb;
  wire [1:0]Z; //Taking outputs as wire
  reg A; // Taking inputs as reg
  reg clock,reset;

// Clock signal is defined in the block below
  always begin 
    clock = 1; 
  	#10; 
  	clock = 0; 
  	#10; 
  end 
  
// Instantiating the topmodule in the test bench to try simulations over it
  fsm top(.reset(reset),.clock(clock),.A(A),.Z(Z));

  initial begin 
//$dumpfile is used to dump the value changes of nets and registers in a file that is named as its argument. 
    $dumpfile("fsm_tb.vcd"); 
 
//Above statement will dump the changes in a file named fsm_tb.vcd (value change dump) which stores all information about value change but, what we are exactly going to dump in this file is told by $dumpvars
    
    $dumpvars(0,fsm_tb); 
 /* 
When level is set to 0, and only the module name is specified, it dumps all the variables of that module and all the variables in ALL lower level modules instantiated by this module. 
If any module in not instantiated by this top module, then its variable will not be 
covered. 
 */ 

    A = 0;
    reset = 1;
    #20;
    reset = 0;
    #20;
    A = 1;
    #100;
    A = 0;
    #100;
    A = 1;
    #20;
    reset = 1;
    #20;
    $finish;
  end
endmodule

fsm_tb.vcd
$date
	Tue Feb 22 22:49:52 2022
$end
$version
	Icarus Verilog
$end
$timescale
	1ns
$end
$scope module fsm_tb $end
$var wire 2 ! Z [1:0] $end
$var reg 1 " A $end
$var reg 1 # clock $end
$var reg 1 $ reset $end
$scope module top $end
$var wire 1 " A $end
$var wire 2 % Z [1:0] $end
$var wire 1 # clock $end
$var wire 1 $ reset $end
$var reg 2 & next_state [1:0] $end
$var reg 2 ' present_state [1:0] $end
$upscope $end
$upscope $end
$enddefinitions $end
#0
$dumpvars
b0 '
b11 &
b0 %
1$
1#
0"
b0 !
$end
#10
0#
#20
b10 &
b11 !
b11 %
b11 '
1#
0$
#30
0#
#40
b0 !
b0 %
b0 '
b1 &
1#
1"
#50
0#
#60
b10 &
b1 !
b1 %
b1 '
1#
#70
0#
#80
b11 &
b10 !
b10 %
b10 '
1#
#90
0#
#100
b0 &
b11 !
b11 %
b11 '
1#
#110
0#
#120
b1 &
b0 !
b0 %
b0 '
1#
#130
0#
#140
b11 !
b11 %
b11 '
b10 &
1#
0"
#150
0#
#160
b1 &
b10 !
b10 %
b10 '
1#
#170
0#
#180
b0 &
b1 !
b1 %
b1 '
1#
#190
0#
#200
b11 &
b0 !
b0 %
b0 '
1#
#210
0#
#220
b10 &
b11 !
b11 %
b11 '
1#
#230
0#
#240
b0 !
b0 %
b0 '
b1 &
1#
1"
#250
0#
#260
1#
1$
